bmitestfile20211/bmi_module.py
bmitestfile20211/bmi_print.py
bmitestfile20211-0.0.0.1.dist-info/METADATA
bmitestfile20211-0.0.0.1.dist-info/WHEEL
bmitestfile20211-0.0.0.1.dist-info/top_level.txt
bmitestfile20211-0.0.0.1.dist-info/RECORD
