Metadata-Version: 2.1
Name: bmitestfile20211
Version: 0.0.0.1
Summary: Bmi calculate and print
Home-page: http://lingua.blog.me/...
Author: YongRokNo
Author-email: nyrog12@gmail.com
License: MIT
Platform: UNKNOWN
Requires-Python: >=3
